AUTHORS.rst
CONTRIBUTING.rst
HISTORY.rst
LICENSE
MANIFEST.in
README.rst
setup.cfg
setup.py
diststack/__init__.py
diststack/cli.py
diststack/diststack.py
diststack.egg-info/PKG-INFO
diststack.egg-info/SOURCES.txt
diststack.egg-info/dependency_links.txt
diststack.egg-info/entry_points.txt
diststack.egg-info/not-zip-safe
diststack.egg-info/requires.txt
diststack.egg-info/top_level.txt
docs/Makefile
docs/authors.rst
docs/conf.py
docs/contributing.rst
docs/history.rst
docs/index.rst
docs/installation.rst
docs/make.bat
docs/readme.rst
docs/usage.rst
tests/__init__.py
tests/test_diststack.py