Metadata-Version: 2.1
Name: diststack
Version: 0.1.0
Summary: Distributed Decentralized Stack
Home-page: https://github.com/asteriogonzalez/diststack
Author: Asterio
Author-email: asterio.gonzalez@gmail.com
License: MIT license
Keywords: diststack
Platform: UNKNOWN
Classifier: Development Status :: 2 - Pre-Alpha
Classifier: Intended Audience :: Developers
Classifier: License :: OSI Approved :: MIT License
Classifier: Natural Language :: English
Classifier: Programming Language :: Python :: 3
Classifier: Programming Language :: Python :: 3.6
Classifier: Programming Language :: Python :: 3.7
Classifier: Programming Language :: Python :: 3.8
Requires-Python: >=3.6
License-File: LICENSE
License-File: AUTHORS.rst
